sklearn2/__init__.py
sklearn2/automl.py
sklearn2/automl_models.py
sklearn2/covariance.py
sklearn2/datasets.py
sklearn2/decomposition.py
sklearn2/feature_extraction.py
sklearn2/feature_selection.py
sklearn2/metrics.py
sklearn2/model_selection.py
sklearn2/pipeline_test.py
sklearn2/utils.py
sklearn2/visualisation.py
sklearn2-0.0.12.dist-info/METADATA
sklearn2-0.0.12.dist-info/RECORD
sklearn2-0.0.12.dist-info/WHEEL
sklearn2-0.0.12.dist-info/top_level.txt
